MagadlalComExam/__init__.py
MagadlalComExam/module.py
magadlalcomexam-0.1.0.dist-info/METADATA
magadlalcomexam-0.1.0.dist-info/WHEEL
magadlalcomexam-0.1.0.dist-info/top_level.txt
magadlalcomexam-0.1.0.dist-info/RECORD
