Metadata-Version: 2.4
Name: MagadlalComExam
Version: 0.1.0
Summary: Online Exam Tool for www.magadlal.com
Author-email: Makhgal Ganbold <makhgal@num.edu.mn>
License: Proprietary
Requires-Python: >=3.12
Requires-Dist: requests
